setup.py
GB_distributions2004/Binomialdistribution.py
GB_distributions2004/Gaussiandistribution.py
GB_distributions2004/Generaldistribution.py
GB_distributions2004/__init__.py
GB_distributions2004.egg-info/PKG-INFO
GB_distributions2004.egg-info/SOURCES.txt
GB_distributions2004.egg-info/dependency_links.txt
GB_distributions2004.egg-info/not-zip-safe
GB_distributions2004.egg-info/top_level.txt