Metadata-Version: 1.0
Name: GB-distributions2004
Version: 1.0
Summary: Gaussian and Binomial distributions
Home-page: UNKNOWN
Author: Nguyễn Đức Tâm
Author-email: tamnd04@gmail.com
License: UNKNOWN
Platform: UNKNOWN
